Metadata-Version: 1.0
Name: pylint-web2py2
Version: 0.8
Summary: pylint_web2py2 is a disciple of pylint-web2py with better web2py support
Home-page: https://github.com/flagist0/pylint_web2py2
Author: Alexander Presnyakov
Author-email: flagist0@gmail.com
License: GPLv2
Keywords: pylint web2py plugin
Platform: UNKNOWN
